README.md
setup.py
mailtransfer/__init__.py
mailtransfer/mailtransfer.py
mailtransfer/main.py
mailtransfer/utils.py
mailtransfer.egg-info/PKG-INFO
mailtransfer.egg-info/SOURCES.txt
mailtransfer.egg-info/dependency_links.txt
mailtransfer.egg-info/entry_points.txt
mailtransfer.egg-info/top_level.txt