Metadata-Version: 1.0
Name: mailtransfer
Version: 1.3
Summary: Simple linux tool for transfer mails from one mailserver to another mailserver
Home-page: https://github.com/amakeenk/mailtransfer
Author: Alexander Makeenkov
Author-email: whoami.tut@gmail.com
License: UNKNOWN
Platform: UNKNOWN
